MANIFEST.in
setup.py
Flask_Marcos.egg-info/PKG-INFO
Flask_Marcos.egg-info/SOURCES.txt
Flask_Marcos.egg-info/dependency_links.txt
Flask_Marcos.egg-info/entry_points.txt
Flask_Marcos.egg-info/requires.txt
Flask_Marcos.egg-info/top_level.txt
docs/Makefile
docs/__init__.py
docs/docs_services.py
docs/make.bat
docs/notes
docs/build/doctrees/Inicio_rapido.doctree
docs/build/doctrees/README.doctree
docs/build/doctrees/api.doctree
docs/build/doctrees/environment.pickle
docs/build/doctrees/index.doctree
docs/build/doctrees/instalacion.doctree
docs/build/doctrees/patrones_de_diseno.doctree
docs/build/doctrees/tutoriales.doctree
docs/build/html/.DS_Store
docs/build/html/.buildinfo
docs/build/html/Archive.zip
docs/build/html/Inicio_rapido.html
docs/build/html/README.html
docs/build/html/api.html
docs/build/html/genindex.html
docs/build/html/index.html
docs/build/html/instalacion.html
docs/build/html/objects.inv
docs/build/html/patrones_de_diseno.html
docs/build/html/search.html
docs/build/html/searchindex.js
docs/build/html/tutoriales.html
docs/build/html/_images/logo-full.png
docs/build/html/_sources/Inicio_rapido.txt
docs/build/html/_sources/README.txt
docs/build/html/_sources/api.txt
docs/build/html/_sources/index.txt
docs/build/html/_sources/instalacion.txt
docs/build/html/_sources/patrones_de_diseno.txt
docs/build/html/_sources/tutoriales.txt
docs/build/html/_static/ajax-loader.gif
docs/build/html/_static/basic.css
docs/build/html/_static/comment-bright.png
docs/build/html/_static/comment-close.png
docs/build/html/_static/comment.png
docs/build/html/_static/debugger.png
docs/build/html/_static/doctools.js
docs/build/html/_static/down-pressed.png
docs/build/html/_static/down.png
docs/build/html/_static/file.png
docs/build/html/_static/flask.png
docs/build/html/_static/flaskr.png
docs/build/html/_static/flasky.css
docs/build/html/_static/jquery.js
docs/build/html/_static/logo-full.png
docs/build/html/_static/minus.png
docs/build/html/_static/no.png
docs/build/html/_static/plus.png
docs/build/html/_static/pygments.css
docs/build/html/_static/searchtools.js
docs/build/html/_static/small_flask.css
docs/build/html/_static/touch-icon.png
docs/build/html/_static/translations.js
